provider/__init__.py
provider/constants.py
provider/forms.py
provider/models.py
provider/scope.py
provider/sphinx.py
provider/urls.py
provider/utils.py
provider/views.py
provider/compat/__init__.py
provider/compat/urls.py
provider/migrations/0001_initial.py
provider/migrations/__init__.py
provider/oauth2/__init__.py
provider/oauth2/admin.py
provider/oauth2/apps.py
provider/oauth2/backends.py
provider/oauth2/forms.py
provider/oauth2/managers.py
provider/oauth2/models.py
provider/oauth2/tests.py
provider/oauth2/urls.py
provider/oauth2/views.py
provider/oauth2/fixtures/test_oauth2.json
provider/oauth2/migrations/__init__.py
provider/templates/provider/authorize.html
provider/templatetags/__init__.py
provider/templatetags/scope.py
provider/tests/__init__.py
provider/tests/test_utils.py
django_oauth2_provider_ng-0.5.0.dist-info/LICENSE
django_oauth2_provider_ng-0.5.0.dist-info/METADATA
django_oauth2_provider_ng-0.5.0.dist-info/WHEEL
django_oauth2_provider_ng-0.5.0.dist-info/top_level.txt
django_oauth2_provider_ng-0.5.0.dist-info/RECORD
