Metadata-Version: 2.1
Name: django-oauth2-provider-ng
Version: 0.5.0
Summary: Provide OAuth2 access to your app
Home-page: https://github.com/ifanrx/django-oauth2-provider
Author: ifanr
Author-email: ifanrx@ifanr.com
Classifier: Environment :: Web Environment
Classifier: Intended Audience :: Developers
Classifier: License :: OSI Approved :: MIT License
Classifier: Operating System :: OS Independent
Classifier: Programming Language :: Python
Classifier: Framework :: Django
License-File: LICENSE
Requires-Dist: shortuuid (>=0.4)
Requires-Dist: six
